attr/__init__.py
attr/__init__.pyi
attr/_cmp.py
attr/_cmp.pyi
attr/_compat.py
attr/_config.py
attr/_funcs.py
attr/_make.py
attr/_next_gen.py
attr/_version_info.py
attr/_version_info.pyi
attr/converters.py
attr/converters.pyi
attr/exceptions.py
attr/exceptions.pyi
attr/filters.py
attr/filters.pyi
attr/py.typed
attr/setters.py
attr/setters.pyi
attr/validators.py
attr/validators.pyi
attrs/__init__.py
attrs/__init__.pyi
attrs/converters.py
attrs/exceptions.py
attrs/filters.py
attrs/py.typed
attrs/setters.py
attrs/validators.py
attrs-21.3.0.dist-info/AUTHORS.rst
attrs-21.3.0.dist-info/LICENSE
attrs-21.3.0.dist-info/METADATA
attrs-21.3.0.dist-info/WHEEL
attrs-21.3.0.dist-info/top_level.txt
attrs-21.3.0.dist-info/RECORD
