Metadata-Version: 2.1
Name: attrs
Version: 21.3.0
Summary: Classes Without Boilerplate
Home-page: https://www.attrs.org/
Author: Hynek Schlawack
Author-email: hs@ox.cx
Maintainer: Hynek Schlawack
Maintainer-email: hs@ox.cx
License: MIT
Project-URL: Documentation, https://www.attrs.org/
Project-URL: Changelog, https://www.attrs.org/en/stable/changelog.html
Project-URL: Bug Tracker, https://github.com/python-attrs/attrs/issues
Project-URL: Source Code, https://github.com/python-attrs/attrs
Project-URL: Funding, https://github.com/sponsors/hynek
Project-URL: Tidelift, https://tidelift.com/subscription/pkg/pypi-attrs?utm_source=pypi-attrs&utm_medium=pypi
Project-URL: Ko-fi, https://ko-fi.com/the_hynek
Keywords: class,attribute,boilerplate
Platform: UNKNOWN
Classifier: Development Status :: 5 - Production/Stable
Classifier: Intended Audience :: Developers
Classifier: Natural Language :: English
Classifier: License :: OSI Approved :: MIT License
Classifier: Operating System :: OS Independent
Classifier: Programming Language :: Python
Classifier: Programming Language :: Python :: 2
Classifier: Programming Language :: Python :: 2.7
Classifier: Programming Language :: Python :: 3
Classifier: Programming Language :: Python :: 3.5
Classifier: Programming Language :: Python :: 3.6
Classifier: Programming Language :: Python :: 3.7
Classifier: Programming Language :: Python :: 3.8
Classifier: Programming Language :: Python :: 3.9
Classifier: Programming Language :: Python :: 3.10
Classifier: Programming Language :: Python :: Implementation :: CPython
Classifier: Programming Language :: Python :: Implementation :: PyPy
Classifier: Topic :: Software Development :: Libraries :: Python Modules
Requires-Python: >=2.7, !=3.0.*, !=3.1.*, !=3.2.*, !=3.3.*, !=3.4.*
Provides-Extra: docs
Provides-Extra: tests_no_zope
Provides-Extra: tests
Provides-Extra: dev
License-File: LICENSE
License-File: AUTHORS.rst
